thicket/__init__.py
thicket/byteify.py
thicket/collection.py
thicket/dirs.py
thicket/files.py
thicket/finders.py
thicket/paths.py
thicket/processors.py
thicket/utils.py
thicket/videos.py
thicket/ffmpeg_wrapper/__init__.py
thicket/ffmpeg_wrapper/probe.py
thicket/ffmpeg_wrapper/utils.py
thicket-0.29.7.dist-info/METADATA
thicket-0.29.7.dist-info/RECORD
thicket-0.29.7.dist-info/WHEEL
thicket-0.29.7.dist-info/top_level.txt
